dtmcli/__init__.py
dtmcli/barrier.py
dtmcli/dtmimp.py
dtmcli/msg.py
dtmcli/saga.py
dtmcli/tcc.py
dtmcli/transbase.py
dtmcli/utils.py
dtmcli-1.7.7.0.dist-info/LICENSE
dtmcli-1.7.7.0.dist-info/METADATA
dtmcli-1.7.7.0.dist-info/WHEEL
dtmcli-1.7.7.0.dist-info/top_level.txt
dtmcli-1.7.7.0.dist-info/RECORD
