Metadata-Version: 2.1
Name: dtmcli
Version: 1.7.7.0
Summary: python client for dtm
Home-page: https://github.com/dtm-labs/dtmcli-py
Author: yedf2
Author-email: 120050102@qq.com
License: UNKNOWN
Platform: UNKNOWN
Classifier: Programming Language :: Python :: 3
Classifier: License :: OSI Approved :: MIT License
Classifier: Operating System :: OS Independent
License-File: LICENSE
Requires-Dist: requests (>=2.1.0)
Requires-Dist: pymysql (>=1.0.1)
